streamcat/__init__.py
streamcat/core.py
streamcat-0.2.1.dist-info/DESCRIPTION.rst
streamcat-0.2.1.dist-info/METADATA
streamcat-0.2.1.dist-info/RECORD
streamcat-0.2.1.dist-info/WHEEL
streamcat-0.2.1.dist-info/metadata.json
streamcat-0.2.1.dist-info/top_level.txt
