Metadata-Version: 2.0
Name: streamcat
Version: 0.2.1
Summary: Encode and decode concatenated objects as streams
Home-page: https://github.com/cryptosense/streamcat
Author: Bertrand Bonnefoy-Claudet
Author-email: bertrand@cryptosense.com
License: MIT
Download-URL: https://github.com/cryptosense/streamcat/tarball/v0.2.1
Keywords: stream,file,json
Platform: UNKNOWN
Classifier: Intended Audience :: Developers
Classifier: License :: OSI Approved :: BSD License
Classifier: Programming Language :: Python :: 2
Classifier: Programming Language :: Python :: 2.7
Classifier: Programming Language :: Python :: 3
Classifier: Programming Language :: Python :: 3.4
Classifier: Programming Language :: Python :: 3.5
Classifier: Programming Language :: Python :: 3.6
Classifier: Programming Language :: Python :: Implementation :: CPython
Classifier: Programming Language :: Python :: Implementation :: PyPy
